package com.sec.factory.aporiented.athandler;

import android.content.Context;

public class AtKeyhold
  extends AtCommandHandler
{
  public AtKeyhold(Context paramContext)
  {
    super(paramContext);
    this.CMD_NAME = "KEYHOLD";
    this.CLASS_NAME = "AtKeyHold";
    this.NUM_ARGS = 1;
  }
  
  /* Error */
  public String handleCommand(String[] paramArrayOfString)
  {
    // Byte code:
    //   0: aload_0
    //   1: monitorenter
    //   2: aload_1
    //   3: arraylength
    //   4: aload_0
    //   5: getfield 23	com/sec/factory/aporiented/athandler/AtKeyhold:NUM_ARGS	I
    //   8: if_icmpeq +10 -> 18
    //   11: ldc 27
    //   13: astore_3
    //   14: aload_0
    //   15: monitorexit
    //   16: aload_3
    //   17: areturn
    //   18: getstatic 31	com/sec/factory/aporiented/athandler/AtKeyhold:mModuleDFT	Lcom/sec/factory/modules/ModuleDFT;
    //   21: aload_1
    //   22: iconst_0
    //   23: aaload
    //   24: invokevirtual 37	com/sec/factory/modules/ModuleDFT:DftKeyHold	(Ljava/lang/String;)V
    //   27: ldc 39
    //   29: astore_3
    //   30: goto -16 -> 14
    //   33: astore_2
    //   34: aload_0
    //   35: monitorexit
    //   36: aload_2
    //   37: athrow
    // Local variable table:
    //   start	length	slot	name	signature
    //   0	38	0	this	AtKeyhold
    //   0	38	1	paramArrayOfString	String[]
    //   33	4	2	localObject	Object
    //   13	17	3	str	String
    // Exception table:
    //   from	to	target	type
    //   2	11	33	finally
    //   18	27	33	finally
  }
}


/* Location:           bin\dex2jar\jar\FactoryTest.jar
 * Qualified Name:     com.sec.factory.aporiented.athandler.AtKeyhold
 * JD-Core Version:    0.7.1
 */