package com.sec.factory.aporiented.athandler;

import android.content.Context;

public class AtMicsd
  extends AtCommandHandler
{
  public AtMicsd(Context paramContext)
  {
    super(paramContext);
    this.CMD_NAME = "MICSD";
    this.CLASS_NAME = "AtMicsd";
    this.NUM_ARGS = 0;
  }
  
  /* Error */
  public String handleCommand(String[] paramArrayOfString)
  {
    // Byte code:
    //   0: aload_0
    //   1: monitorenter
    //   2: aload_1
    //   3: arraylength
    //   4: aload_0
    //   5: getfield 23	com/sec/factory/aporiented/athandler/AtMicsd:NUM_ARGS	I
    //   8: if_icmpeq +10 -> 18
    //   11: ldc 27
    //   13: astore_3
    //   14: aload_0
    //   15: monitorexit
    //   16: aload_3
    //   17: areturn
    //   18: aload_0
    //   19: invokevirtual 31	com/sec/factory/aporiented/athandler/AtMicsd:getCmdType	()I
    //   22: ifne +9 -> 31
    //   25: aload_0
    //   26: bipush 10
    //   28: invokevirtual 35	com/sec/factory/aporiented/athandler/AtMicsd:setResultType	(I)V
    //   31: aload_0
    //   32: getfield 39	com/sec/factory/aporiented/athandler/AtMicsd:context	Landroid/content/Context;
    //   35: invokestatic 45	com/sec/factory/modules/ModuleDFT:instance	(Landroid/content/Context;)Lcom/sec/factory/modules/ModuleDFT;
    //   38: invokevirtual 49	com/sec/factory/modules/ModuleDFT:DftMicsd	()Ljava/lang/String;
    //   41: astore 4
    //   43: aload 4
    //   45: astore_3
    //   46: goto -32 -> 14
    //   49: astore_2
    //   50: aload_0
    //   51: monitorexit
    //   52: aload_2
    //   53: athrow
    // Local variable table:
    //   start	length	slot	name	signature
    //   0	54	0	this	AtMicsd
    //   0	54	1	paramArrayOfString	String[]
    //   49	4	2	localObject1	Object
    //   13	33	3	localObject2	Object
    //   41	3	4	str	String
    // Exception table:
    //   from	to	target	type
    //   2	11	49	finally
    //   18	31	49	finally
    //   31	43	49	finally
  }
}


/* Location:           bin\dex2jar\jar\FactoryTest.jar
 * Qualified Name:     com.sec.factory.aporiented.athandler.AtMicsd
 * JD-Core Version:    0.7.1
 */